[
  {
    "checkerPackId": "taint-flow-golang-default",
    "checkerIds": [
      "taint_flow_gin_input",
      "taint_flow_go_input",
      "cobra.Command-builtIn",
      "go-restful-entryPoints-collect-checker",
      "beego-entrypoint-collect-checker",
      "gorilla-mux-entrypoint-collect-checker",
      "gRpc-entryPoint-collect-checker",
      "go-main-entryPoints-collection",
      "sync.Once.Do-builtIn",
      "urfave-cli-builtIn",
      "callgraph",
      "sanitizer"
    ],
    "description": "golang污点追踪-对外默认使用规则包"
  },
  {
    "checkerPackId": "taint-flow-golang-inner",
    "checkerIds": [
      "taint_flow_gin_input_inner",
      "cobra.Command-builtIn",
      "go-restful-entryPoints-collect-checker",
      "beego-entrypoint-collect-checker",
      "gorilla-mux-entrypoint-collect-checker",
      "gRpc-entryPoint-collect-checker",
      "go-main-entryPoints-collection",
      "sync.Once.Do-builtIn",
      "urfave-cli-builtIn",
      "callgraph",
      "sanitizer"
    ],
    "description": "golang污点追踪-蚂蚁内部使用的规则包"

  },
  {
    "checkerPackId": "taint-flow-java-default",
    "checkerIds": [
      "taint_flow_java_input",
      "callgraph",
      "sanitizer"
    ],
    "description": "java污点追踪-对外默认使用的规则包"
  },
  {
    "checkerPackId": "taint-flow-java-inner",
    "checkerIds": [
      "taint_flow_java_input_inner",
      "callgraph",
      "sanitizer"
    ],
    "description": "java污点追踪-蚂蚁内部使用的规则包"
  },
  {
    "checkerPackId": "taint-flow-javascript-default",
    "checkerIds": [
      "taint_flow_js_input",
      "taint_flow_egg_input",
      "callgraph",
      "sanitizer"
    ],
    "description": "js污点追踪-对外默认使用的规则包"
  },
  {
    "checkerPackId": "taint-flow-javascript-inner",
    "checkerIds": [
      "taint_flow_egg_input",
      "taint_flow_express_input",
      "callgraph",
      "sanitizer"
    ],
    "description": "js污点追踪-蚂蚁内部使用的规则包"
  },
  {
    "checkerPackId": "taint-flow-express",
    "checkerIds": [
      "taint_flow_express_input",
      "callgraph",
      "sanitizer"
    ],
    "description": "Express 污点追踪"
  },
  {
    "checkerPackId": "taint-flow-python-default",
    "checkerIds": [
      "taint_flow_python_input",
      "taint_flow_python_django_input",
      "taint_flow_python_tornado_input",
      "taint_flow_python_httpserver_input",
      "callgraph",
      "sanitizer"
    ],
    "description": "python污点追踪-对外默认使用的规则包"
  },
  {
    "checkerPackId": "taint-flow-python-inner",
    "checkerIds": [
      "taint_flow_python_input_inner",
      "taint_flow_python_django_input",
      "taint_flow_python_tornado_input",
      "taint_flow_python_httpserver_input",
      "callgraph",
      "sanitizer"
    ],
    "description": "python污点追踪-蚂蚁内部使用的规则包"
  },
  {
    "checkerPackId": "antql-dataflow-inner",
    "checkerIds": [
      "antql_getbaseclass",
      "antql_getdefinition",
      "antql_getsubclass",
      "antql_hasflow",
      "antql_hasfunctioncall",
      "antql_hasproperty",
      "callgraph"
    ],
    "description": "antql数据流-蚂蚁内部使用的规则包"
  },
  {
    "checkerPackId": "java-sdk-inner",
    "checkerIds": [
      "get_file_ast",
      "get_ast_source_code",
      "callgraph"
    ],
    "description": "java的sdk-蚂蚁内部使用的规则包"
  },
  {
    "checkerPackId": "callchain-java",
    "checkerIds": [
      "callchain_java"
    ],
    "description": "Java callchain checker - 只检测sink匹配"
  },
  {
    "checkerPackId": "callchain-go",
    "checkerIds": [
      "callchain_go"
    ],
    "description": "Go callchain checker - 只检测sink匹配"
  },
  {
    "checkerPackId": "callchain-js",
    "checkerIds": [
      "callchain_js"
    ],
    "description": "JavaScript callchain checker - 只检测sink匹配"
  },
  {
    "checkerPackId": "callchain-python",
    "checkerIds": [
      "callchain_python"
    ],
    "description": "Python callchain checker - 只检测sink匹配"
  },
  {
    "checkerPackId": "taint-flow-php-default",
    "checkerIds": [
      "taint_flow_php_input",
      "callgraph",
      "sanitizer"
    ],
    "description": "PHP污点追踪-对外默认使用的规则包"
  },
  {
    "checkerPackId": "callchain-php",
    "checkerIds": [
      "callchain_php"
    ],
    "description": "PHP callchain checker - 只检测sink匹配"
  }
]
